quickscript.py
quickscript-0.2.0.dist-info/METADATA
quickscript-0.2.0.dist-info/WHEEL
quickscript-0.2.0.dist-info/top_level.txt
quickscript-0.2.0.dist-info/RECORD
